simple_flask_google_login/__init__.py
simple_flask_google_login-0.3.0.dist-info/LICENSE
simple_flask_google_login-0.3.0.dist-info/METADATA
simple_flask_google_login-0.3.0.dist-info/WHEEL
simple_flask_google_login-0.3.0.dist-info/top_level.txt
simple_flask_google_login-0.3.0.dist-info/RECORD
