Metadata-Version: 2.1
Name: simple-flask-google-login
Version: 0.3.0
Summary: Convenience utility for implementing Google login with Flask.
Author-email: Alvin Wan <hi@alvinwan.com>
License: Apache License
Project-URL: Homepage, https://github.com/alvinwan/simple-flask-google-login
Keywords: flask,google,login,tutorial
Classifier: Programming Language :: Python
Classifier: Programming Language :: Python :: 3
Requires-Python: >=3.8
License-File: LICENSE
Requires-Dist: flask
Requires-Dist: google-auth-oauthlib
